README.md
setup.py
pylint_doc_spacing/__init__.py
pylint_doc_spacing.egg-info/PKG-INFO
pylint_doc_spacing.egg-info/SOURCES.txt
pylint_doc_spacing.egg-info/dependency_links.txt
pylint_doc_spacing.egg-info/requires.txt
pylint_doc_spacing.egg-info/top_level.txt