Metadata-Version: 1.1
Name: pylint-doc-spacing
Version: 0.0.4
Summary: PyLint plugin to check the presence or not of a blank line after any documentation.
Home-page: https://github.com/bayesimpact/pylint-doc-spacing
Author: Pascal Corpet
Author-email: pascal@bayesimpact.org
License: The MIT License (MIT)
Download-URL: https://github.com/bayesimpact/pylint-doc-spacing/tarball/0.0.4
Keywords: PyLint,plugin,convention,spacing
Platform: UNKNOWN
